{
  "accountAssociation": {
    "header": "eyJmaWQiOjIzMzA1NiwidHlwZSI6ImN1c3RvZHkiLCJrZXkiOiIweDA0MmU1QTRkYjQ1ZjhiMmVlNzJCQWY5MmYyYTg1ZTg2N0EzOTcxZGEifQ",
    "payload": "eyJkb21haW4iOiJ0aWN0YWN0b2UtdGhyZWUtZXRhLnZlcmNlbC5hcHAifQ",
    "signature": "MHg5MDFkODFiMTJiN2RiYTRjOGFiNTMwNDAwZDY1YThiZDljNmNjNjU1ODczNmIzMDk0Y2VjZjQ1OTJlMGJiMGZjNjFlNDg0OTFmOWRiZGYwNTZiZmNhYWNiZDI2MzJlNDJkZjdmMjQxZGFhMjBlYmEwZjY2YzlmOTRjMjQyNWUwYTFi"
  },
  "miniapp": {
    "version": "1",
    "name": "TicTacToe Pro",
    "iconUrl": "https://tictactoe-three-eta.vercel.app/icon.png",
    "homeUrl": "https://tictactoe-three-eta.vercel.app",
    "imageUrl": "https://tictactoe-three-eta.vercel.app/og-image.svg",
    "buttonTitle": "🎮 Play Now",
    "splashImageUrl": "https://tictactoe-three-eta.vercel.app/splash.svg",
    "splashBackgroundColor": "#000000",
    "webhookUrl": "https://tictactoe-three-eta.vercel.app/api/webhook",
    "description": "Play 6x6 TicTacToe with 4-in-a-row winning conditions, multiplayer battles, and onchain rewards on Base.",
    "subtitle": "Strategic XO with Blockchain Rewards",
    "screenshotUrls": [
      "https://tictactoe-three-eta.vercel.app/screenshot-portrait.svg"
    ],
    "primaryCategory": "games",
    "tags": ["gaming", "strategy", "multiplayer", "blockchain", "base", "onchain"],
    "heroImageUrl": "https://tictactoe-three-eta.vercel.app/hero.svg",
    "tagline": "Master the grid, earn onchain rewards!",
    "ogTitle": "TicTacToe Pro - Onchain Gaming on Base",
    "ogDescription": "Experience strategic 6x6 TicTacToe with blockchain-verified results and transparent leaderboards.",
    "ogImageUrl": "https://tictactoe-three-eta.vercel.app/og-image.svg",
    "requiredChains": ["eip155:8453"],
    "requiredCapabilities": [
      "actions.ready",
      "actions.signIn",
      "actions.composeCast",
      "wallet.getEthereumProvider"
    ]
  }
}